robust_stats-0.1.1.dist-info/METADATA
robust_stats-0.1.1.dist-info/WHEEL
robust_stats-0.1.1.dist-info/license_files/LICENSE
robust_stats.libs/libquadmath-1c3f8ec4.so.0
robust_stats.libs/libgfortran-df5d6f8d.so.5
robust_stats/__init__.py
robust_stats/robust_mean.py
robust_stats/robust_stats.cpython-311-x86_64-linux-gnu.so
robust_stats-0.1.1.dist-info/RECORD
